{
  "id": "Ezreal",
  "name_ja": "エズリアル",
  "patches": [
    {
      "patch_name": "ワイルドリフト パッチノート 7.1",
      "updatetime": "2026/04/14",
      "data": [
        {
          "lane": "ADC",
          "rank": "Emerald",
          "winrate": 49.3673,
          "pickrate": 8.3752,
          "banrate": 0.1928
        },
        {
          "lane": "ADC",
          "rank": "Diamond",
          "winrate": 49.7195,
          "pickrate": 8.791599999999999,
          "banrate": 0.095
        },
        {
          "lane": "ADC",
          "rank": "Master",
          "winrate": 50.1579,
          "pickrate": 9.5835,
          "banrate": 0.1362
        }
      ]
    },
    {
      "patch_name": "ワイルドリフト パッチノート 7.1b",
      "updatetime": "2026/05/05",
      "data": [
        {
          "lane": "ADC",
          "rank": "Emerald",
          "winrate": 50.586,
          "pickrate": 8.3936,
          "banrate": 0.2841
        },
        {
          "lane": "ADC",
          "rank": "Diamond",
          "winrate": 50.9663,
          "pickrate": 9.0678,
          "banrate": 0.189
        },
        {
          "lane": "ADC",
          "rank": "Master",
          "winrate": 51.179300000000005,
          "pickrate": 9.1891,
          "banrate": 0.1936
        },
        {
          "lane": "ADC",
          "rank": "Challenger",
          "winrate": 51.587,
          "pickrate": 10.9872,
          "banrate": 0.1878
        },
        {
          "lane": "ADC",
          "rank": "Legendary_rank",
          "winrate": 50.509899999999995,
          "pickrate": 12.6789,
          "banrate": 0.25339999999999996
        }
      ]
    },
    {
      "patch_name": "ワイルドリフト パッチノート 7.1d",
      "updatetime": "2026/05/12",
      "data": [
        {
          "lane": "ADC",
          "rank": "Emerald",
          "winrate": 50.042699999999996,
          "pickrate": 8.895,
          "banrate": 0.35040000000000004
        },
        {
          "lane": "ADC",
          "rank": "Diamond",
          "winrate": 50.1606,
          "pickrate": 9.658,
          "banrate": 0.2084
        },
        {
          "lane": "ADC",
          "rank": "Master",
          "winrate": 49.9364,
          "pickrate": 9.8505,
          "banrate": 0.2079
        },
        {
          "lane": "ADC",
          "rank": "Challenger",
          "winrate": 50.932599999999994,
          "pickrate": 10.857700000000001,
          "banrate": 0.1406
        },
        {
          "lane": "ADC",
          "rank": "Legendary_rank",
          "winrate": 49.9495,
          "pickrate": 13.5919,
          "banrate": 0.24520000000000003
        }
      ]
    },
    {
      "patch_name": "ワイルドリフト パッチノート 7.1e",
      "updatetime": "2026/05/26",
      "data": [
        {
          "lane": "ADC",
          "rank": "Emerald",
          "winrate": 50.119899999999994,
          "pickrate": 9.3309,
          "banrate": 0.3166
        },
        {
          "lane": "ADC",
          "rank": "Diamond",
          "winrate": 50.71600000000001,
          "pickrate": 10.5958,
          "banrate": 0.2557
        },
        {
          "lane": "ADC",
          "rank": "Master",
          "winrate": 50.710100000000004,
          "pickrate": 10.7296,
          "banrate": 0.2607
        },
        {
          "lane": "ADC",
          "rank": "Challenger",
          "winrate": 50.804700000000004,
          "pickrate": 11.6814,
          "banrate": 0.2052
        },
        {
          "lane": "ADC",
          "rank": "Legendary_rank",
          "winrate": 51.220600000000005,
          "pickrate": 13.947000000000001,
          "banrate": 0.35609999999999997
        }
      ]
    },
    {
      "patch_name": "ワイルドリフト パッチノート 7.1f",
      "updatetime": "2026/06/12",
      "data": [
        {
          "lane": "ADC",
          "rank": "Emerald",
          "winrate": 49.897000000000006,
          "pickrate": 11.0153,
          "banrate": 0.45189999999999997
        },
        {
          "lane": "ADC",
          "rank": "Diamond",
          "winrate": 50.409400000000005,
          "pickrate": 11.4,
          "banrate": 0.33
        },
        {
          "lane": "ADC",
          "rank": "Master",
          "winrate": 50.505599999999994,
          "pickrate": 11.394400000000001,
          "banrate": 0.3364
        },
        {
          "lane": "ADC",
          "rank": "Challenger",
          "winrate": 50.8416,
          "pickrate": 11.945400000000001,
          "banrate": 0.2799
        },
        {
          "lane": "ADC",
          "rank": "Legendary_rank",
          "winrate": 50.125600000000006,
          "pickrate": 14.909600000000001,
          "banrate": 0.615
        }
      ]
    }
  ]
}